nonebot_plugin_sendmsg_by_bots/__init__.py
nonebot_plugin_sendmsg_by_bots/config.py
nonebot_plugin_sendmsg_by_bots/tools.py
nonebot_plugin_sendmsg_by_bots-0.2.0.dist-info/WHEEL
nonebot_plugin_sendmsg_by_bots-0.2.0.dist-info/METADATA
nonebot_plugin_sendmsg_by_bots-0.2.0.dist-info/RECORD
