Metadata-Version: 2.1
Name: nonebot-plugin-sendmsg-by-bots
Version: 0.2.0
Summary: a send msg tools
License: MIT
Author-email: nek0us <nekouss@gmail.com>
Requires-Python: >=3.8
Requires-Dist: nonebot-adapter-onebot>=2.1.3
Requires-Dist: nonebot2>=2.0.0
Requires-Dist: nonebot_plugin_htmlrender
Project-URL: Homepage, https://github.com/nek0us/nonebot-plugin-sendmsg-by-bots
Project-URL: Repository, https://github.com/nek0us/nonebot-plugin-sendmsg-by-bots
